{
	"cmake" : 
	{
		"generator" : 
		{
			"multiConfig" : false,
			"name" : "MinGW Makefiles"
		},
		"paths" : 
		{
			"cmake" : "C:/CMake/bin/cmake.exe",
			"cpack" : "C:/CMake/bin/cpack.exe",
			"ctest" : "C:/CMake/bin/ctest.exe",
			"root" : "C:/CMake/share/cmake-3.29"
		},
		"version" : 
		{
			"isDirty" : false,
			"major" : 3,
			"minor" : 29,
			"patch" : 0,
			"string" : "3.29.0-rc4",
			"suffix" : "rc4"
		}
	},
	"objects" : 
	[
		{
			"jsonFile" : "codemodel-v2-c9509bb703a23924d98b.json",
			"kind" : "codemodel",
			"version" : 
			{
				"major" : 2,
				"minor" : 7
			}
		},
		{
			"jsonFile" : "cache-v2-5b42150bdfd528b193fe.json",
			"kind" : "cache",
			"version" : 
			{
				"major" : 2,
				"minor" : 0
			}
		},
		{
			"jsonFile" : "cmakeFiles-v1-5f17ec1a648c48efe17b.json",
			"kind" : "cmakeFiles",
			"version" : 
			{
				"major" : 1,
				"minor" : 0
			}
		},
		{
			"jsonFile" : "toolchains-v1-94efd7c52760cd71f426.json",
			"kind" : "toolchains",
			"version" : 
			{
				"major" : 1,
				"minor" : 0
			}
		}
	],
	"reply" : 
	{
		"client-vscode" : 
		{
			"query.json" : 
			{
				"requests" : 
				[
					{
						"kind" : "cache",
						"version" : 2
					},
					{
						"kind" : "codemodel",
						"version" : 2
					},
					{
						"kind" : "toolchains",
						"version" : 1
					},
					{
						"kind" : "cmakeFiles",
						"version" : 1
					}
				],
				"responses" : 
				[
					{
						"jsonFile" : "cache-v2-5b42150bdfd528b193fe.json",
						"kind" : "cache",
						"version" : 
						{
							"major" : 2,
							"minor" : 0
						}
					},
					{
						"jsonFile" : "codemodel-v2-c9509bb703a23924d98b.json",
						"kind" : "codemodel",
						"version" : 
						{
							"major" : 2,
							"minor" : 7
						}
					},
					{
						"jsonFile" : "toolchains-v1-94efd7c52760cd71f426.json",
						"kind" : "toolchains",
						"version" : 
						{
							"major" : 1,
							"minor" : 0
						}
					},
					{
						"jsonFile" : "cmakeFiles-v1-5f17ec1a648c48efe17b.json",
						"kind" : "cmakeFiles",
						"version" : 
						{
							"major" : 1,
							"minor" : 0
						}
					}
				]
			}
		}
	}
}
